betterLogs4Python/__init__.py
betterLogs4Python-0.1.8.dist-info/LICENSE
betterLogs4Python-0.1.8.dist-info/METADATA
betterLogs4Python-0.1.8.dist-info/WHEEL
betterLogs4Python-0.1.8.dist-info/top_level.txt
betterLogs4Python-0.1.8.dist-info/RECORD
