Metadata-Version: 2.1
Name: betterLogs4Python
Version: 0.1.8
Summary: As the name says, it's a little helper for logging more comfortably in python 3 (for now only python3 support) to file and console!
Home-page: https://github.com/JonasMayerDev/betterLogs4Python
Author: Jonas Mayer
Author-email: jonas.mayer.dev@gmail.com
License: UNKNOWN
Project-URL: Bug Tracker, https://github.com/JonasMayerDev/betterLogs4Python/issues
Platform: UNKNOWN
Classifier: Programming Language :: Python :: 3
Classifier: License :: OSI Approved :: MIT License
Classifier: Operating System :: OS Independent
Requires-Python: >=3.5
License-File: LICENSE
